pymediainfo-6.1.0.data/data/docs/License.html
pymediainfo-6.1.0.data/purelib/pymediainfo/MediaInfo.dll
pymediainfo-6.1.0.data/purelib/pymediainfo/__init__.py
pymediainfo-6.1.0.dist-info/AUTHORS
pymediainfo-6.1.0.dist-info/LICENSE
pymediainfo-6.1.0.dist-info/METADATA
pymediainfo-6.1.0.dist-info/WHEEL
pymediainfo-6.1.0.dist-info/namespace_packages.txt
pymediainfo-6.1.0.dist-info/top_level.txt
pymediainfo-6.1.0.dist-info/RECORD
